{
  "glob": {
    "n": "59643",
    "b": "-0.0629501",
    "e": "1.68893"
  },
  "v_4": {
    "n": "19418",
    "b": "-0.145331",
    "e": "2.35645"
  },
  "v_119": {
    "n": "40225",
    "b": "-0.0231821",
    "e": "1.24456"
  },
  "v_4_o_5": {
    "n": "19418",
    "b": "-0.145331",
    "e": "2.35645"
  },
  "v_119_o_7": {
    "n": "40225",
    "b": "-0.0231821",
    "e": "1.24456"
  },
  "v_4_o_5_l_1": {
    "n": "1892",
    "b": "0.311743",
    "e": "2.11194"
  },
  "v_4_o_5_l_10": {
    "n": "3863",
    "b": "-0.316678",
    "e": "2.05566"
  },
  "v_4_o_5_l_9": {
    "n": "2645",
    "b": "-0.463577",
    "e": "1.8555"
  },
  "v_4_o_5_l_8": {
    "n": "2004",
    "b": "-0.652056",
    "e": "2.73814"
  },
  "v_4_o_5_l_7": {
    "n": "1574",
    "b": "-0.399815",
    "e": "3.89381"
  },
  "v_4_o_5_l_6": {
    "n": "1337",
    "b": "0.312202",
    "e": "2.41398"
  },
  "v_4_o_5_l_5": {
    "n": "1225",
    "b": "0.415321",
    "e": "1.71366"
  },
  "v_4_o_5_l_4": {
    "n": "1290",
    "b": "0.118528",
    "e": "2.19931"
  },
  "v_4_o_5_l_3": {
    "n": "1432",
    "b": "0.118843",
    "e": "2.11078"
  },
  "v_4_o_5_l_2": {
    "n": "2156",
    "b": "-0.127829",
    "e": "2.26475"
  },
  "v_119_o_7_l_16": {
    "n": "5772",
    "b": "-0.107214",
    "e": "0.201899"
  },
  "v_119_o_7_l_15": {
    "n": "4320",
    "b": "0.237949",
    "e": "2.58402"
  },
  "v_119_o_7_l_14": {
    "n": "3958",
    "b": "0.0528484",
    "e": "1.40032"
  },
  "v_119_o_7_l_13": {
    "n": "3958",
    "b": "0.0312668",
    "e": "1.43676"
  },
  "v_119_o_7_l_12": {
    "n": "4430",
    "b": "-0.0305053",
    "e": "1.41793"
  },
  "v_119_o_7_l_11": {
    "n": "4430",
    "b": "-0.0283609",
    "e": "1.34692"
  },
  "v_119_o_7_l_19": {
    "n": "3180",
    "b": "-0.0978488",
    "e": "0.136785"
  },
  "v_119_o_7_l_18": {
    "n": "4405",
    "b": "-0.0990274",
    "e": "0.15676"
  },
  "v_119_o_7_l_17": {
    "n": "5772",
    "b": "-0.11545",
    "e": "0.177743"
  },
  "s_19": {
    "n": "40225",
    "b": "-0.0231821",
    "e": "1.24456"
  },
  "s_19_c_7": {
    "n": "3180",
    "b": "-0.0978488",
    "e": "0.136785"
  },
  "s_19_c_8": {
    "n": "4405",
    "b": "-0.0990274",
    "e": "0.15676"
  },
  "s_19_c_9": {
    "n": "5772",
    "b": "-0.11545",
    "e": "0.177743"
  },
  "s_19_c_10": {
    "n": "5772",
    "b": "-0.107214",
    "e": "0.201899"
  },
  "s_19_c_17": {
    "n": "4320",
    "b": "0.237949",
    "e": "2.58402"
  },
  "s_19_c_19": {
    "n": "3958",
    "b": "0.0528484",
    "e": "1.40032"
  },
  "s_19_c_20": {
    "n": "3958",
    "b": "0.0312668",
    "e": "1.43676"
  },
  "s_19_c_21": {
    "n": "4430",
    "b": "-0.0305053",
    "e": "1.41793"
  },
  "s_19_c_22": {
    "n": "4430",
    "b": "-0.0283609",
    "e": "1.34692"
  },
  "v_4_g_C4": {
    "n": "2025",
    "b": "-0.40837",
    "e": "2.8376"
  },
  "v_4_g_C5": {
    "n": "1548",
    "b": "0.185294",
    "e": "1.61496"
  },
  "v_4_g_o:euratl": {
    "n": "3304",
    "b": "-0.159544",
    "e": "2.44961"
  },
  "v_4_g_o:europe": {
    "n": "3304",
    "b": "-0.159524",
    "e": "2.44962"
  },
  "v_4_g_o:metcoop": {
    "n": "2091",
    "b": "-0.0705664",
    "e": "1.84857"
  },
  "v_4_g_o:nord20": {
    "n": "3573",
    "b": "-0.151147",
    "e": "2.3861"
  },
  "v_119_g_C4": {
    "n": "2771",
    "b": "0.113478",
    "e": "1.31204"
  },
  "v_119_g_C5": {
    "n": "4463",
    "b": "-0.101565",
    "e": "1.18148"
  },
  "v_119_g_o:euratl": {
    "n": "6633",
    "b": "-0.0236163",
    "e": "1.25963"
  },
  "v_119_g_o:europe": {
    "n": "6385",
    "b": "-0.0126586",
    "e": "1.2738"
  },
  "v_119_g_o:metcoop": {
    "n": "5505",
    "b": "-0.0505928",
    "e": "1.23684"
  },
  "v_119_g_o:nord20": {
    "n": "7234",
    "b": "-0.0191923",
    "e": "1.23313"
  },
  "v_4_o_5_g_C4": {
    "n": "2025",
    "b": "-0.40837",
    "e": "2.8376"
  },
  "v_4_o_5_g_C5": {
    "n": "1548",
    "b": "0.185294",
    "e": "1.61496"
  },
  "v_4_o_5_g_o:euratl": {
    "n": "3304",
    "b": "-0.159544",
    "e": "2.44961"
  },
  "v_4_o_5_g_o:europe": {
    "n": "3304",
    "b": "-0.159524",
    "e": "2.44962"
  },
  "v_4_o_5_g_o:metcoop": {
    "n": "2091",
    "b": "-0.0705664",
    "e": "1.84857"
  },
  "v_4_o_5_g_o:nord20": {
    "n": "3573",
    "b": "-0.151147",
    "e": "2.3861"
  },
  "v_119_o_7_g_C4": {
    "n": "2771",
    "b": "0.113478",
    "e": "1.31204"
  },
  "v_119_o_7_g_C5": {
    "n": "4463",
    "b": "-0.101565",
    "e": "1.18148"
  },
  "v_119_o_7_g_o:euratl": {
    "n": "6633",
    "b": "-0.0236163",
    "e": "1.25963"
  },
  "v_119_o_7_g_o:europe": {
    "n": "6385",
    "b": "-0.0126586",
    "e": "1.2738"
  },
  "v_119_o_7_g_o:metcoop": {
    "n": "5505",
    "b": "-0.0505928",
    "e": "1.23684"
  },
  "v_119_o_7_g_o:nord20": {
    "n": "7234",
    "b": "-0.0191923",
    "e": "1.23313"
  },
  "v_4_o_5_l_1_g_C4": {
    "n": "188",
    "b": "0.210724",
    "e": "2.59912"
  },
  "v_4_o_5_l_1_g_C5": {
    "n": "161",
    "b": "0.284577",
    "e": "1.41623"
  },
  "v_4_o_5_l_1_g_o:euratl": {
    "n": "322",
    "b": "0.321467",
    "e": "2.17851"
  },
  "v_4_o_5_l_1_g_o:europe": {
    "n": "322",
    "b": "0.321467",
    "e": "2.17851"
  },
  "v_4_o_5_l_1_g_o:metcoop": {
    "n": "201",
    "b": "0.62932",
    "e": "1.73305"
  },
  "v_4_o_5_l_1_g_o:nord20": {
    "n": "349",
    "b": "0.244794",
    "e": "2.13642"
  },
  "v_4_o_5_l_10_g_C4": {
    "n": "474",
    "b": "-0.470244",
    "e": "2.22813"
  },
  "v_4_o_5_l_10_g_C5": {
    "n": "251",
    "b": "0.0843536",
    "e": "1.70644"
  },
  "v_4_o_5_l_10_g_o:euratl": {
    "n": "658",
    "b": "-0.363896",
    "e": "2.08845"
  },
  "v_4_o_5_l_10_g_o:europe": {
    "n": "658",
    "b": "-0.363797",
    "e": "2.0885"
  },
  "v_4_o_5_l_10_g_o:metcoop": {
    "n": "372",
    "b": "-0.374738",
    "e": "1.89196"
  },
  "v_4_o_5_l_10_g_o:nord20": {
    "n": "725",
    "b": "-0.278149",
    "e": "2.06255"
  },
  "v_4_o_5_l_9_g_C4": {
    "n": "282",
    "b": "-0.488199",
    "e": "1.87191"
  },
  "v_4_o_5_l_9_g_C5": {
    "n": "200",
    "b": "-0.402287",
    "e": "1.80598"
  },
  "v_4_o_5_l_9_g_o:euratl": {
    "n": "448",
    "b": "-0.463237",
    "e": "1.86368"
  },
  "v_4_o_5_l_9_g_o:europe": {
    "n": "448",
    "b": "-0.463237",
    "e": "1.86368"
  },
  "v_4_o_5_l_9_g_o:metcoop": {
    "n": "303",
    "b": "-0.517206",
    "e": "1.88177"
  },
  "v_4_o_5_l_9_g_o:nord20": {
    "n": "482",
    "b": "-0.452551",
    "e": "1.84484"
  },
  "v_4_o_5_l_8_g_C4": {
    "n": "203",
    "b": "-1.67829",
    "e": "3.67536"
  },
  "v_4_o_5_l_8_g_C5": {
    "n": "164",
    "b": "0.389944",
    "e": "1.07194"
  },
  "v_4_o_5_l_8_g_o:euratl": {
    "n": "341",
    "b": "-0.844113",
    "e": "2.92307"
  },
  "v_4_o_5_l_8_g_o:europe": {
    "n": "341",
    "b": "-0.844113",
    "e": "2.92307"
  },
  "v_4_o_5_l_8_g_o:metcoop": {
    "n": "221",
    "b": "0.448829",
    "e": "1.35485"
  },
  "v_4_o_5_l_8_g_o:nord20": {
    "n": "367",
    "b": "-0.754067",
    "e": "2.82584"
  },
  "v_4_o_5_l_7_g_C4": {
    "n": "152",
    "b": "-1.5401",
    "e": "5.35543"
  },
  "v_4_o_5_l_7_g_C5": {
    "n": "136",
    "b": "0.621684",
    "e": "1.32603"
  },
  "v_4_o_5_l_7_g_o:euratl": {
    "n": "268",
    "b": "-0.601315",
    "e": "4.13793"
  },
  "v_4_o_5_l_7_g_o:europe": {
    "n": "268",
    "b": "-0.601315",
    "e": "4.13793"
  },
  "v_4_o_5_l_7_g_o:metcoop": {
    "n": "174",
    "b": "0.813987",
    "e": "2.26321"
  },
  "v_4_o_5_l_7_g_o:nord20": {
    "n": "288",
    "b": "-0.519257",
    "e": "3.99591"
  },
  "v_4_o_5_l_6_g_C4": {
    "n": "130",
    "b": "0.443444",
    "e": "2.97293"
  },
  "v_4_o_5_l_6_g_C5": {
    "n": "115",
    "b": "0.262536",
    "e": "1.30453"
  },
  "v_4_o_5_l_6_g_o:euratl": {
    "n": "228",
    "b": "0.351808",
    "e": "2.41978"
  },
  "v_4_o_5_l_6_g_o:europe": {
    "n": "228",
    "b": "0.351808",
    "e": "2.41978"
  },
  "v_4_o_5_l_6_g_o:metcoop": {
    "n": "146",
    "b": "-0.0447182",
    "e": "2.7286"
  },
  "v_4_o_5_l_6_g_o:nord20": {
    "n": "245",
    "b": "0.358528",
    "e": "2.34276"
  },
  "v_4_o_5_l_5_g_C4": {
    "n": "116",
    "b": "0.215856",
    "e": "1.72655"
  },
  "v_4_o_5_l_5_g_C5": {
    "n": "108",
    "b": "0.692708",
    "e": "1.68247"
  },
  "v_4_o_5_l_5_g_o:euratl": {
    "n": "209",
    "b": "0.491828",
    "e": "1.75782"
  },
  "v_4_o_5_l_5_g_o:europe": {
    "n": "209",
    "b": "0.491828",
    "e": "1.75782"
  },
  "v_4_o_5_l_5_g_o:metcoop": {
    "n": "135",
    "b": "0.026882",
    "e": "1.61304"
  },
  "v_4_o_5_l_5_g_o:nord20": {
    "n": "224",
    "b": "0.445767",
    "e": "1.70544"
  },
  "v_4_o_5_l_4_g_C4": {
    "n": "126",
    "b": "0.374971",
    "e": "2.81047"
  },
  "v_4_o_5_l_4_g_C5": {
    "n": "110",
    "b": "-0.0732921",
    "e": "1.37647"
  },
  "v_4_o_5_l_4_g_o:euratl": {
    "n": "220",
    "b": "0.222923",
    "e": "2.32435"
  },
  "v_4_o_5_l_4_g_o:europe": {
    "n": "220",
    "b": "0.222923",
    "e": "2.32435"
  },
  "v_4_o_5_l_4_g_o:metcoop": {
    "n": "142",
    "b": "-0.441816",
    "e": "1.33112"
  },
  "v_4_o_5_l_4_g_o:nord20": {
    "n": "236",
    "b": "0.166035",
    "e": "2.25837"
  },
  "v_4_o_5_l_3_g_C4": {
    "n": "139",
    "b": "-0.139233",
    "e": "1.93953"
  },
  "v_4_o_5_l_3_g_C5": {
    "n": "123",
    "b": "0.392974",
    "e": "2.34946"
  },
  "v_4_o_5_l_3_g_o:euratl": {
    "n": "244",
    "b": "0.248634",
    "e": "2.16446"
  },
  "v_4_o_5_l_3_g_o:europe": {
    "n": "244",
    "b": "0.248634",
    "e": "2.16446"
  },
  "v_4_o_5_l_3_g_o:metcoop": {
    "n": "158",
    "b": "-0.24112",
    "e": "1.75814"
  },
  "v_4_o_5_l_3_g_o:nord20": {
    "n": "262",
    "b": "0.11062",
    "e": "2.14177"
  },
  "v_4_o_5_l_2_g_C4": {
    "n": "215",
    "b": "-0.194368",
    "e": "2.71032"
  },
  "v_4_o_5_l_2_g_C5": {
    "n": "180",
    "b": "0.0362469",
    "e": "1.69123"
  },
  "v_4_o_5_l_2_g_o:euratl": {
    "n": "366",
    "b": "-0.0748407",
    "e": "2.37062"
  },
  "v_4_o_5_l_2_g_o:europe": {
    "n": "366",
    "b": "-0.0748407",
    "e": "2.37062"
  },
  "v_4_o_5_l_2_g_o:metcoop": {
    "n": "239",
    "b": "-0.481264",
    "e": "1.66432"
  },
  "v_4_o_5_l_2_g_o:nord20": {
    "n": "395",
    "b": "-0.0892777",
    "e": "2.30256"
  },
  "v_119_o_7_l_16_g_C4": {
    "n": "482",
    "b": "-0.0940414",
    "e": "0.190066"
  },
  "v_119_o_7_l_16_g_C5": {
    "n": "557",
    "b": "-0.122041",
    "e": "0.213024"
  },
  "v_119_o_7_l_16_g_o:euratl": {
    "n": "968",
    "b": "-0.105753",
    "e": "0.200522"
  },
  "v_119_o_7_l_16_g_o:europe": {
    "n": "917",
    "b": "-0.098096",
    "e": "0.195365"
  },
  "v_119_o_7_l_16_g_o:metcoop": {
    "n": "770",
    "b": "-0.112471",
    "e": "0.20795"
  },
  "v_119_o_7_l_16_g_o:nord20": {
    "n": "1039",
    "b": "-0.109052",
    "e": "0.202697"
  },
  "v_119_o_7_l_15_g_C4": {
    "n": "268",
    "b": "1.26341",
    "e": "2.87499"
  },
  "v_119_o_7_l_15_g_C5": {
    "n": "508",
    "b": "-0.300757",
    "e": "2.38075"
  },
  "v_119_o_7_l_15_g_o:euratl": {
    "n": "707",
    "b": "0.308481",
    "e": "2.61144"
  },
  "v_119_o_7_l_15_g_o:europe": {
    "n": "686",
    "b": "0.314146",
    "e": "2.64107"
  },
  "v_119_o_7_l_15_g_o:metcoop": {
    "n": "599",
    "b": "0.0616163",
    "e": "2.56968"
  },
  "v_119_o_7_l_15_g_o:nord20": {
    "n": "776",
    "b": "0.239446",
    "e": "2.56224"
  },
  "v_119_o_7_l_14_g_C4": {
    "n": "249",
    "b": "0.218696",
    "e": "1.55947"
  },
  "v_119_o_7_l_14_g_C5": {
    "n": "464",
    "b": "-0.0308326",
    "e": "1.27988"
  },
  "v_119_o_7_l_14_g_o:euratl": {
    "n": "648",
    "b": "0.0408067",
    "e": "1.4352"
  },
  "v_119_o_7_l_14_g_o:europe": {
    "n": "628",
    "b": "0.051514",
    "e": "1.4478"
  },
  "v_119_o_7_l_14_g_o:metcoop": {
    "n": "543",
    "b": "0.055136",
    "e": "1.36609"
  },
  "v_119_o_7_l_14_g_o:nord20": {
    "n": "713",
    "b": "0.0563062",
    "e": "1.38394"
  },
  "v_119_o_7_l_13_g_C4": {
    "n": "249",
    "b": "0.111175",
    "e": "1.54014"
  },
  "v_119_o_7_l_13_g_C5": {
    "n": "464",
    "b": "-0.00202662",
    "e": "1.35191"
  },
  "v_119_o_7_l_13_g_o:euratl": {
    "n": "648",
    "b": "0.0131848",
    "e": "1.46827"
  },
  "v_119_o_7_l_13_g_o:europe": {
    "n": "628",
    "b": "0.0293767",
    "e": "1.47902"
  },
  "v_119_o_7_l_13_g_o:metcoop": {
    "n": "543",
    "b": "0.0304511",
    "e": "1.41271"
  },
  "v_119_o_7_l_13_g_o:nord20": {
    "n": "713",
    "b": "0.0375067",
    "e": "1.42048"
  },
  "v_119_o_7_l_12_g_C4": {
    "n": "283",
    "b": "0.0829863",
    "e": "1.53705"
  },
  "v_119_o_7_l_12_g_C5": {
    "n": "511",
    "b": "-0.077828",
    "e": "1.32693"
  },
  "v_119_o_7_l_12_g_o:euratl": {
    "n": "728",
    "b": "-0.0498453",
    "e": "1.44199"
  },
  "v_119_o_7_l_12_g_o:europe": {
    "n": "706",
    "b": "-0.0261578",
    "e": "1.44581"
  },
  "v_119_o_7_l_12_g_o:metcoop": {
    "n": "614",
    "b": "-0.0513529",
    "e": "1.40499"
  },
  "v_119_o_7_l_12_g_o:nord20": {
    "n": "794",
    "b": "-0.0205075",
    "e": "1.40543"
  },
  "v_119_o_7_l_11_g_C4": {
    "n": "283",
    "b": "0.136602",
    "e": "1.50757"
  },
  "v_119_o_7_l_11_g_C5": {
    "n": "511",
    "b": "-0.102187",
    "e": "1.23947"
  },
  "v_119_o_7_l_11_g_o:euratl": {
    "n": "728",
    "b": "-0.0429951",
    "e": "1.3663"
  },
  "v_119_o_7_l_11_g_o:europe": {
    "n": "706",
    "b": "-0.017004",
    "e": "1.36617"
  },
  "v_119_o_7_l_11_g_o:metcoop": {
    "n": "614",
    "b": "-0.0678355",
    "e": "1.32351"
  },
  "v_119_o_7_l_11_g_o:nord20": {
    "n": "794",
    "b": "-0.0170802",
    "e": "1.34118"
  },
  "v_119_o_7_l_19_g_C4": {
    "n": "198",
    "b": "-0.0909254",
    "e": "0.129663"
  },
  "v_119_o_7_l_19_g_C5": {
    "n": "377",
    "b": "-0.0976903",
    "e": "0.13761"
  },
  "v_119_o_7_l_19_g_o:euratl": {
    "n": "516",
    "b": "-0.101197",
    "e": "0.139476"
  },
  "v_119_o_7_l_19_g_o:europe": {
    "n": "496",
    "b": "-0.0996706",
    "e": "0.138852"
  },
  "v_119_o_7_l_19_g_o:metcoop": {
    "n": "443",
    "b": "-0.101597",
    "e": "0.138471"
  },
  "v_119_o_7_l_19_g_o:nord20": {
    "n": "575",
    "b": "-0.0953608",
    "e": "0.134926"
  },
  "v_119_o_7_l_18_g_C4": {
    "n": "277",
    "b": "-0.129287",
    "e": "0.171518"
  },
  "v_119_o_7_l_18_g_C5": {
    "n": "514",
    "b": "-0.077839",
    "e": "0.146049"
  },
  "v_119_o_7_l_18_g_o:euratl": {
    "n": "722",
    "b": "-0.10199",
    "e": "0.158636"
  },
  "v_119_o_7_l_18_g_o:europe": {
    "n": "701",
    "b": "-0.101629",
    "e": "0.159034"
  },
  "v_119_o_7_l_18_g_o:metcoop": {
    "n": "609",
    "b": "-0.104881",
    "e": "0.156993"
  },
  "v_119_o_7_l_18_g_o:nord20": {
    "n": "791",
    "b": "-0.0958541",
    "e": "0.155442"
  },
  "v_119_o_7_l_17_g_C4": {
    "n": "482",
    "b": "-0.143742",
    "e": "0.193909"
  },
  "v_119_o_7_l_17_g_C5": {
    "n": "557",
    "b": "-0.0869841",
    "e": "0.160265"
  },
  "v_119_o_7_l_17_g_o:euratl": {
    "n": "968",
    "b": "-0.117684",
    "e": "0.179538"
  },
  "v_119_o_7_l_17_g_o:europe": {
    "n": "917",
    "b": "-0.115621",
    "e": "0.17834"
  },
  "v_119_o_7_l_17_g_o:metcoop": {
    "n": "770",
    "b": "-0.121079",
    "e": "0.179084"
  },
  "v_119_o_7_l_17_g_o:nord20": {
    "n": "1039",
    "b": "-0.113314",
    "e": "0.176671"
  },
  "s_19_g_C4": {
    "n": "2771",
    "b": "0.113478",
    "e": "1.31204"
  },
  "s_19_g_C5": {
    "n": "4463",
    "b": "-0.101565",
    "e": "1.18148"
  },
  "s_19_g_o:euratl": {
    "n": "6633",
    "b": "-0.0236163",
    "e": "1.25963"
  },
  "s_19_g_o:europe": {
    "n": "6385",
    "b": "-0.0126586",
    "e": "1.2738"
  },
  "s_19_g_o:metcoop": {
    "n": "5505",
    "b": "-0.0505928",
    "e": "1.23684"
  },
  "s_19_g_o:nord20": {
    "n": "7234",
    "b": "-0.0191923",
    "e": "1.23313"
  },
  "s_19_c_7_g_C4": {
    "n": "198",
    "b": "-0.0909254",
    "e": "0.129663"
  },
  "s_19_c_7_g_C5": {
    "n": "377",
    "b": "-0.0976903",
    "e": "0.13761"
  },
  "s_19_c_7_g_o:euratl": {
    "n": "516",
    "b": "-0.101197",
    "e": "0.139476"
  },
  "s_19_c_7_g_o:europe": {
    "n": "496",
    "b": "-0.0996706",
    "e": "0.138852"
  },
  "s_19_c_7_g_o:metcoop": {
    "n": "443",
    "b": "-0.101597",
    "e": "0.138471"
  },
  "s_19_c_7_g_o:nord20": {
    "n": "575",
    "b": "-0.0953608",
    "e": "0.134926"
  },
  "s_19_c_8_g_C4": {
    "n": "277",
    "b": "-0.129287",
    "e": "0.171518"
  },
  "s_19_c_8_g_C5": {
    "n": "514",
    "b": "-0.077839",
    "e": "0.146049"
  },
  "s_19_c_8_g_o:euratl": {
    "n": "722",
    "b": "-0.10199",
    "e": "0.158636"
  },
  "s_19_c_8_g_o:europe": {
    "n": "701",
    "b": "-0.101629",
    "e": "0.159034"
  },
  "s_19_c_8_g_o:metcoop": {
    "n": "609",
    "b": "-0.104881",
    "e": "0.156993"
  },
  "s_19_c_8_g_o:nord20": {
    "n": "791",
    "b": "-0.0958541",
    "e": "0.155442"
  },
  "s_19_c_9_g_C4": {
    "n": "482",
    "b": "-0.143742",
    "e": "0.193909"
  },
  "s_19_c_9_g_C5": {
    "n": "557",
    "b": "-0.0869841",
    "e": "0.160265"
  },
  "s_19_c_9_g_o:euratl": {
    "n": "968",
    "b": "-0.117684",
    "e": "0.179538"
  },
  "s_19_c_9_g_o:europe": {
    "n": "917",
    "b": "-0.115621",
    "e": "0.17834"
  },
  "s_19_c_9_g_o:metcoop": {
    "n": "770",
    "b": "-0.121079",
    "e": "0.179084"
  },
  "s_19_c_9_g_o:nord20": {
    "n": "1039",
    "b": "-0.113314",
    "e": "0.176671"
  },
  "s_19_c_10_g_C4": {
    "n": "482",
    "b": "-0.0940414",
    "e": "0.190066"
  },
  "s_19_c_10_g_C5": {
    "n": "557",
    "b": "-0.122041",
    "e": "0.213024"
  },
  "s_19_c_10_g_o:euratl": {
    "n": "968",
    "b": "-0.105753",
    "e": "0.200522"
  },
  "s_19_c_10_g_o:europe": {
    "n": "917",
    "b": "-0.098096",
    "e": "0.195365"
  },
  "s_19_c_10_g_o:metcoop": {
    "n": "770",
    "b": "-0.112471",
    "e": "0.20795"
  },
  "s_19_c_10_g_o:nord20": {
    "n": "1039",
    "b": "-0.109052",
    "e": "0.202697"
  },
  "s_19_c_17_g_C4": {
    "n": "268",
    "b": "1.26341",
    "e": "2.87499"
  },
  "s_19_c_17_g_C5": {
    "n": "508",
    "b": "-0.300757",
    "e": "2.38075"
  },
  "s_19_c_17_g_o:euratl": {
    "n": "707",
    "b": "0.308481",
    "e": "2.61144"
  },
  "s_19_c_17_g_o:europe": {
    "n": "686",
    "b": "0.314146",
    "e": "2.64107"
  },
  "s_19_c_17_g_o:metcoop": {
    "n": "599",
    "b": "0.0616163",
    "e": "2.56968"
  },
  "s_19_c_17_g_o:nord20": {
    "n": "776",
    "b": "0.239446",
    "e": "2.56224"
  },
  "s_19_c_19_g_C4": {
    "n": "249",
    "b": "0.218696",
    "e": "1.55947"
  },
  "s_19_c_19_g_C5": {
    "n": "464",
    "b": "-0.0308326",
    "e": "1.27988"
  },
  "s_19_c_19_g_o:euratl": {
    "n": "648",
    "b": "0.0408067",
    "e": "1.4352"
  },
  "s_19_c_19_g_o:europe": {
    "n": "628",
    "b": "0.051514",
    "e": "1.4478"
  },
  "s_19_c_19_g_o:metcoop": {
    "n": "543",
    "b": "0.055136",
    "e": "1.36609"
  },
  "s_19_c_19_g_o:nord20": {
    "n": "713",
    "b": "0.0563062",
    "e": "1.38394"
  },
  "s_19_c_20_g_C4": {
    "n": "249",
    "b": "0.111175",
    "e": "1.54014"
  },
  "s_19_c_20_g_C5": {
    "n": "464",
    "b": "-0.00202662",
    "e": "1.35191"
  },
  "s_19_c_20_g_o:euratl": {
    "n": "648",
    "b": "0.0131848",
    "e": "1.46827"
  },
  "s_19_c_20_g_o:europe": {
    "n": "628",
    "b": "0.0293767",
    "e": "1.47902"
  },
  "s_19_c_20_g_o:metcoop": {
    "n": "543",
    "b": "0.0304511",
    "e": "1.41271"
  },
  "s_19_c_20_g_o:nord20": {
    "n": "713",
    "b": "0.0375067",
    "e": "1.42048"
  },
  "s_19_c_21_g_C4": {
    "n": "283",
    "b": "0.0829863",
    "e": "1.53705"
  },
  "s_19_c_21_g_C5": {
    "n": "511",
    "b": "-0.077828",
    "e": "1.32693"
  },
  "s_19_c_21_g_o:euratl": {
    "n": "728",
    "b": "-0.0498453",
    "e": "1.44199"
  },
  "s_19_c_21_g_o:europe": {
    "n": "706",
    "b": "-0.0261578",
    "e": "1.44581"
  },
  "s_19_c_21_g_o:metcoop": {
    "n": "614",
    "b": "-0.0513529",
    "e": "1.40499"
  },
  "s_19_c_21_g_o:nord20": {
    "n": "794",
    "b": "-0.0205075",
    "e": "1.40543"
  },
  "s_19_c_22_g_C4": {
    "n": "283",
    "b": "0.136602",
    "e": "1.50757"
  },
  "s_19_c_22_g_C5": {
    "n": "511",
    "b": "-0.102187",
    "e": "1.23947"
  },
  "s_19_c_22_g_o:euratl": {
    "n": "728",
    "b": "-0.0429951",
    "e": "1.3663"
  },
  "s_19_c_22_g_o:europe": {
    "n": "706",
    "b": "-0.017004",
    "e": "1.36617"
  },
  "s_19_c_22_g_o:metcoop": {
    "n": "614",
    "b": "-0.0678355",
    "e": "1.32351"
  },
  "s_19_c_22_g_o:nord20": {
    "n": "794",
    "b": "-0.0170802",
    "e": "1.34118"
  }
}
