{
  "glob": {
    "n": "1868",
    "b": "0.22986",
    "e": "1.41532"
  },
  "v_4": {
    "n": "1386",
    "b": "0.356427",
    "e": "1.61073"
  },
  "v_119": {
    "n": "482",
    "b": "-0.134084",
    "e": "0.550271"
  },
  "v_4_o_5": {
    "n": "1386",
    "b": "0.356427",
    "e": "1.61073"
  },
  "v_119_o_7": {
    "n": "482",
    "b": "-0.134084",
    "e": "0.550271"
  },
  "v_4_o_5_l_1": {
    "n": "108",
    "b": "0.558399",
    "e": "0.563406"
  },
  "v_4_o_5_l_10": {
    "n": "360",
    "b": "0.150899",
    "e": "2.03272"
  },
  "v_4_o_5_l_9": {
    "n": "168",
    "b": "-0.279288",
    "e": "1.327"
  },
  "v_4_o_5_l_8": {
    "n": "132",
    "b": "0.403503",
    "e": "2.39901"
  },
  "v_4_o_5_l_7": {
    "n": "102",
    "b": "0.284588",
    "e": "0.95541"
  },
  "v_4_o_5_l_6": {
    "n": "84",
    "b": "0.559013",
    "e": "1.45966"
  },
  "v_4_o_5_l_5": {
    "n": "72",
    "b": "0.89168",
    "e": "1.8213"
  },
  "v_4_o_5_l_4": {
    "n": "90",
    "b": "1.4125",
    "e": "1.58711"
  },
  "v_4_o_5_l_3": {
    "n": "78",
    "b": "1.1087",
    "e": "1.35228"
  },
  "v_4_o_5_l_2": {
    "n": "192",
    "b": "0.100234",
    "e": "0.848778"
  },
  "v_119_o_7_l_16": {
    "n": "99",
    "b": "-0.229163",
    "e": "0.253897"
  },
  "v_119_o_7_l_15": {
    "n": "26",
    "b": "1.19121",
    "e": "1.6137"
  },
  "v_119_o_7_l_14": {
    "n": "26",
    "b": "-0.377085",
    "e": "0.657197"
  },
  "v_119_o_7_l_13": {
    "n": "26",
    "b": "-0.288726",
    "e": "0.602365"
  },
  "v_119_o_7_l_12": {
    "n": "26",
    "b": "-0.276662",
    "e": "0.779416"
  },
  "v_119_o_7_l_11": {
    "n": "26",
    "b": "-0.352076",
    "e": "1.03155"
  },
  "v_119_o_7_l_19": {
    "n": "70",
    "b": "-0.110867",
    "e": "0.122328"
  },
  "v_119_o_7_l_18": {
    "n": "84",
    "b": "-0.147535",
    "e": "0.17729"
  },
  "v_119_o_7_l_17": {
    "n": "99",
    "b": "-0.192936",
    "e": "0.202247"
  },
  "s_19": {
    "n": "482",
    "b": "-0.134084",
    "e": "0.550271"
  },
  "s_19_c_7": {
    "n": "70",
    "b": "-0.110867",
    "e": "0.122328"
  },
  "s_19_c_8": {
    "n": "84",
    "b": "-0.147535",
    "e": "0.17729"
  },
  "s_19_c_9": {
    "n": "99",
    "b": "-0.192936",
    "e": "0.202247"
  },
  "s_19_c_10": {
    "n": "99",
    "b": "-0.229163",
    "e": "0.253897"
  },
  "s_19_c_17": {
    "n": "26",
    "b": "1.19121",
    "e": "1.6137"
  },
  "s_19_c_19": {
    "n": "26",
    "b": "-0.377085",
    "e": "0.657197"
  },
  "s_19_c_20": {
    "n": "26",
    "b": "-0.288726",
    "e": "0.602365"
  },
  "s_19_c_21": {
    "n": "26",
    "b": "-0.276662",
    "e": "0.779416"
  },
  "s_19_c_22": {
    "n": "26",
    "b": "-0.352076",
    "e": "1.03155"
  },
  "v_4_g_C5": {
    "n": "231",
    "b": "0.356427",
    "e": "1.61073"
  },
  "v_4_g_o:euratl": {
    "n": "231",
    "b": "0.356427",
    "e": "1.61073"
  },
  "v_4_g_o:europe": {
    "n": "231",
    "b": "0.356427",
    "e": "1.61073"
  },
  "v_4_g_o:metcoop": {
    "n": "231",
    "b": "0.356427",
    "e": "1.61073"
  },
  "v_4_g_o:nord20": {
    "n": "231",
    "b": "0.356427",
    "e": "1.61073"
  },
  "v_119_g_C5": {
    "n": "108",
    "b": "-0.157648",
    "e": "0.591255"
  },
  "v_119_g_o:euratl": {
    "n": "79",
    "b": "-0.0857625",
    "e": "0.454819"
  },
  "v_119_g_o:europe": {
    "n": "79",
    "b": "-0.0857625",
    "e": "0.454819"
  },
  "v_119_g_o:nord20": {
    "n": "108",
    "b": "-0.157648",
    "e": "0.591255"
  },
  "v_4_o_5_g_C5": {
    "n": "231",
    "b": "0.356427",
    "e": "1.61073"
  },
  "v_4_o_5_g_o:euratl": {
    "n": "231",
    "b": "0.356427",
    "e": "1.61073"
  },
  "v_4_o_5_g_o:europe": {
    "n": "231",
    "b": "0.356427",
    "e": "1.61073"
  },
  "v_4_o_5_g_o:metcoop": {
    "n": "231",
    "b": "0.356427",
    "e": "1.61073"
  },
  "v_4_o_5_g_o:nord20": {
    "n": "231",
    "b": "0.356427",
    "e": "1.61073"
  },
  "v_119_o_7_g_C5": {
    "n": "108",
    "b": "-0.157648",
    "e": "0.591255"
  },
  "v_119_o_7_g_o:euratl": {
    "n": "79",
    "b": "-0.0857625",
    "e": "0.454819"
  },
  "v_119_o_7_g_o:europe": {
    "n": "79",
    "b": "-0.0857625",
    "e": "0.454819"
  },
  "v_119_o_7_g_o:nord20": {
    "n": "108",
    "b": "-0.157648",
    "e": "0.591255"
  },
  "v_4_o_5_l_1_g_C5": {
    "n": "18",
    "b": "0.558399",
    "e": "0.563406"
  },
  "v_4_o_5_l_1_g_o:euratl": {
    "n": "18",
    "b": "0.558399",
    "e": "0.563406"
  },
  "v_4_o_5_l_1_g_o:europe": {
    "n": "18",
    "b": "0.558399",
    "e": "0.563406"
  },
  "v_4_o_5_l_1_g_o:metcoop": {
    "n": "18",
    "b": "0.558399",
    "e": "0.563406"
  },
  "v_4_o_5_l_1_g_o:nord20": {
    "n": "18",
    "b": "0.558399",
    "e": "0.563406"
  },
  "v_4_o_5_l_10_g_C5": {
    "n": "60",
    "b": "0.150899",
    "e": "2.03272"
  },
  "v_4_o_5_l_10_g_o:euratl": {
    "n": "60",
    "b": "0.150899",
    "e": "2.03272"
  },
  "v_4_o_5_l_10_g_o:europe": {
    "n": "60",
    "b": "0.150899",
    "e": "2.03272"
  },
  "v_4_o_5_l_10_g_o:metcoop": {
    "n": "60",
    "b": "0.150899",
    "e": "2.03272"
  },
  "v_4_o_5_l_10_g_o:nord20": {
    "n": "60",
    "b": "0.150899",
    "e": "2.03272"
  },
  "v_4_o_5_l_9_g_C5": {
    "n": "28",
    "b": "-0.279288",
    "e": "1.327"
  },
  "v_4_o_5_l_9_g_o:euratl": {
    "n": "28",
    "b": "-0.279288",
    "e": "1.327"
  },
  "v_4_o_5_l_9_g_o:europe": {
    "n": "28",
    "b": "-0.279288",
    "e": "1.327"
  },
  "v_4_o_5_l_9_g_o:metcoop": {
    "n": "28",
    "b": "-0.279288",
    "e": "1.327"
  },
  "v_4_o_5_l_9_g_o:nord20": {
    "n": "28",
    "b": "-0.279288",
    "e": "1.327"
  },
  "v_4_o_5_l_8_g_C5": {
    "n": "22",
    "b": "0.403503",
    "e": "2.39901"
  },
  "v_4_o_5_l_8_g_o:euratl": {
    "n": "22",
    "b": "0.403503",
    "e": "2.39901"
  },
  "v_4_o_5_l_8_g_o:europe": {
    "n": "22",
    "b": "0.403503",
    "e": "2.39901"
  },
  "v_4_o_5_l_8_g_o:metcoop": {
    "n": "22",
    "b": "0.403503",
    "e": "2.39901"
  },
  "v_4_o_5_l_8_g_o:nord20": {
    "n": "22",
    "b": "0.403503",
    "e": "2.39901"
  },
  "v_4_o_5_l_7_g_C5": {
    "n": "17",
    "b": "0.284588",
    "e": "0.95541"
  },
  "v_4_o_5_l_7_g_o:euratl": {
    "n": "17",
    "b": "0.284588",
    "e": "0.95541"
  },
  "v_4_o_5_l_7_g_o:europe": {
    "n": "17",
    "b": "0.284588",
    "e": "0.95541"
  },
  "v_4_o_5_l_7_g_o:metcoop": {
    "n": "17",
    "b": "0.284588",
    "e": "0.95541"
  },
  "v_4_o_5_l_7_g_o:nord20": {
    "n": "17",
    "b": "0.284588",
    "e": "0.95541"
  },
  "v_4_o_5_l_6_g_C5": {
    "n": "14",
    "b": "0.559013",
    "e": "1.45966"
  },
  "v_4_o_5_l_6_g_o:euratl": {
    "n": "14",
    "b": "0.559013",
    "e": "1.45966"
  },
  "v_4_o_5_l_6_g_o:europe": {
    "n": "14",
    "b": "0.559013",
    "e": "1.45966"
  },
  "v_4_o_5_l_6_g_o:metcoop": {
    "n": "14",
    "b": "0.559013",
    "e": "1.45966"
  },
  "v_4_o_5_l_6_g_o:nord20": {
    "n": "14",
    "b": "0.559013",
    "e": "1.45966"
  },
  "v_4_o_5_l_5_g_C5": {
    "n": "12",
    "b": "0.89168",
    "e": "1.8213"
  },
  "v_4_o_5_l_5_g_o:euratl": {
    "n": "12",
    "b": "0.89168",
    "e": "1.8213"
  },
  "v_4_o_5_l_5_g_o:europe": {
    "n": "12",
    "b": "0.89168",
    "e": "1.8213"
  },
  "v_4_o_5_l_5_g_o:metcoop": {
    "n": "12",
    "b": "0.89168",
    "e": "1.8213"
  },
  "v_4_o_5_l_5_g_o:nord20": {
    "n": "12",
    "b": "0.89168",
    "e": "1.8213"
  },
  "v_4_o_5_l_4_g_C5": {
    "n": "15",
    "b": "1.4125",
    "e": "1.58711"
  },
  "v_4_o_5_l_4_g_o:euratl": {
    "n": "15",
    "b": "1.4125",
    "e": "1.58711"
  },
  "v_4_o_5_l_4_g_o:europe": {
    "n": "15",
    "b": "1.4125",
    "e": "1.58711"
  },
  "v_4_o_5_l_4_g_o:metcoop": {
    "n": "15",
    "b": "1.4125",
    "e": "1.58711"
  },
  "v_4_o_5_l_4_g_o:nord20": {
    "n": "15",
    "b": "1.4125",
    "e": "1.58711"
  },
  "v_4_o_5_l_3_g_C5": {
    "n": "13",
    "b": "1.1087",
    "e": "1.35228"
  },
  "v_4_o_5_l_3_g_o:euratl": {
    "n": "13",
    "b": "1.1087",
    "e": "1.35228"
  },
  "v_4_o_5_l_3_g_o:europe": {
    "n": "13",
    "b": "1.1087",
    "e": "1.35228"
  },
  "v_4_o_5_l_3_g_o:metcoop": {
    "n": "13",
    "b": "1.1087",
    "e": "1.35228"
  },
  "v_4_o_5_l_3_g_o:nord20": {
    "n": "13",
    "b": "1.1087",
    "e": "1.35228"
  },
  "v_4_o_5_l_2_g_C5": {
    "n": "32",
    "b": "0.100234",
    "e": "0.848778"
  },
  "v_4_o_5_l_2_g_o:euratl": {
    "n": "32",
    "b": "0.100234",
    "e": "0.848778"
  },
  "v_4_o_5_l_2_g_o:europe": {
    "n": "32",
    "b": "0.100234",
    "e": "0.848778"
  },
  "v_4_o_5_l_2_g_o:metcoop": {
    "n": "32",
    "b": "0.100234",
    "e": "0.848778"
  },
  "v_4_o_5_l_2_g_o:nord20": {
    "n": "32",
    "b": "0.100234",
    "e": "0.848778"
  },
  "v_119_o_7_l_16_g_C5": {
    "n": "23",
    "b": "-0.216455",
    "e": "0.244825"
  },
  "v_119_o_7_l_16_g_o:euratl": {
    "n": "15",
    "b": "-0.258392",
    "e": "0.273625"
  },
  "v_119_o_7_l_16_g_o:europe": {
    "n": "15",
    "b": "-0.258392",
    "e": "0.273625"
  },
  "v_119_o_7_l_16_g_o:nord20": {
    "n": "23",
    "b": "-0.216455",
    "e": "0.244825"
  },
  "v_119_o_7_l_15_g_C5": {
    "n": "6",
    "b": "0.942495",
    "e": "1.54527"
  },
  "v_119_o_7_l_15_g_o:euratl": {
    "n": "4",
    "b": "1.75082",
    "e": "1.75795"
  },
  "v_119_o_7_l_15_g_o:europe": {
    "n": "4",
    "b": "1.75082",
    "e": "1.75795"
  },
  "v_119_o_7_l_15_g_o:nord20": {
    "n": "6",
    "b": "0.942495",
    "e": "1.54527"
  },
  "v_119_o_7_l_14_g_C5": {
    "n": "6",
    "b": "-0.470876",
    "e": "0.780393"
  },
  "v_119_o_7_l_14_g_o:euratl": {
    "n": "4",
    "b": "-0.166054",
    "e": "0.182816"
  },
  "v_119_o_7_l_14_g_o:europe": {
    "n": "4",
    "b": "-0.166054",
    "e": "0.182816"
  },
  "v_119_o_7_l_14_g_o:nord20": {
    "n": "6",
    "b": "-0.470876",
    "e": "0.780393"
  },
  "v_119_o_7_l_13_g_C5": {
    "n": "6",
    "b": "-0.362905",
    "e": "0.718903"
  },
  "v_119_o_7_l_13_g_o:euratl": {
    "n": "4",
    "b": "-0.121822",
    "e": "0.128039"
  },
  "v_119_o_7_l_13_g_o:europe": {
    "n": "4",
    "b": "-0.121822",
    "e": "0.128039"
  },
  "v_119_o_7_l_13_g_o:nord20": {
    "n": "6",
    "b": "-0.362905",
    "e": "0.718903"
  },
  "v_119_o_7_l_12_g_C5": {
    "n": "6",
    "b": "-0.327634",
    "e": "0.917063"
  },
  "v_119_o_7_l_12_g_o:euratl": {
    "n": "4",
    "b": "-0.161976",
    "e": "0.286494"
  },
  "v_119_o_7_l_12_g_o:europe": {
    "n": "4",
    "b": "-0.161976",
    "e": "0.286494"
  },
  "v_119_o_7_l_12_g_o:nord20": {
    "n": "6",
    "b": "-0.327634",
    "e": "0.917063"
  },
  "v_119_o_7_l_11_g_C5": {
    "n": "6",
    "b": "-0.379011",
    "e": "1.19685"
  },
  "v_119_o_7_l_11_g_o:euratl": {
    "n": "4",
    "b": "-0.291473",
    "e": "0.485044"
  },
  "v_119_o_7_l_11_g_o:europe": {
    "n": "4",
    "b": "-0.291473",
    "e": "0.485044"
  },
  "v_119_o_7_l_11_g_o:nord20": {
    "n": "6",
    "b": "-0.379011",
    "e": "1.19685"
  },
  "v_119_o_7_l_19_g_C5": {
    "n": "14",
    "b": "-0.110867",
    "e": "0.122328"
  },
  "v_119_o_7_l_19_g_o:euratl": {
    "n": "14",
    "b": "-0.110867",
    "e": "0.122328"
  },
  "v_119_o_7_l_19_g_o:europe": {
    "n": "14",
    "b": "-0.110867",
    "e": "0.122328"
  },
  "v_119_o_7_l_19_g_o:nord20": {
    "n": "14",
    "b": "-0.110867",
    "e": "0.122328"
  },
  "v_119_o_7_l_18_g_C5": {
    "n": "18",
    "b": "-0.140655",
    "e": "0.171913"
  },
  "v_119_o_7_l_18_g_o:euratl": {
    "n": "15",
    "b": "-0.159919",
    "e": "0.186577"
  },
  "v_119_o_7_l_18_g_o:europe": {
    "n": "15",
    "b": "-0.159919",
    "e": "0.186577"
  },
  "v_119_o_7_l_18_g_o:nord20": {
    "n": "18",
    "b": "-0.140655",
    "e": "0.171913"
  },
  "v_119_o_7_l_17_g_C5": {
    "n": "23",
    "b": "-0.19026",
    "e": "0.199108"
  },
  "v_119_o_7_l_17_g_o:euratl": {
    "n": "15",
    "b": "-0.199093",
    "e": "0.209287"
  },
  "v_119_o_7_l_17_g_o:europe": {
    "n": "15",
    "b": "-0.199093",
    "e": "0.209287"
  },
  "v_119_o_7_l_17_g_o:nord20": {
    "n": "23",
    "b": "-0.19026",
    "e": "0.199108"
  },
  "s_19_g_C5": {
    "n": "108",
    "b": "-0.157648",
    "e": "0.591255"
  },
  "s_19_g_o:euratl": {
    "n": "79",
    "b": "-0.0857625",
    "e": "0.454819"
  },
  "s_19_g_o:europe": {
    "n": "79",
    "b": "-0.0857625",
    "e": "0.454819"
  },
  "s_19_g_o:nord20": {
    "n": "108",
    "b": "-0.157648",
    "e": "0.591255"
  },
  "s_19_c_7_g_C5": {
    "n": "14",
    "b": "-0.110867",
    "e": "0.122328"
  },
  "s_19_c_7_g_o:euratl": {
    "n": "14",
    "b": "-0.110867",
    "e": "0.122328"
  },
  "s_19_c_7_g_o:europe": {
    "n": "14",
    "b": "-0.110867",
    "e": "0.122328"
  },
  "s_19_c_7_g_o:nord20": {
    "n": "14",
    "b": "-0.110867",
    "e": "0.122328"
  },
  "s_19_c_8_g_C5": {
    "n": "18",
    "b": "-0.140655",
    "e": "0.171913"
  },
  "s_19_c_8_g_o:euratl": {
    "n": "15",
    "b": "-0.159919",
    "e": "0.186577"
  },
  "s_19_c_8_g_o:europe": {
    "n": "15",
    "b": "-0.159919",
    "e": "0.186577"
  },
  "s_19_c_8_g_o:nord20": {
    "n": "18",
    "b": "-0.140655",
    "e": "0.171913"
  },
  "s_19_c_9_g_C5": {
    "n": "23",
    "b": "-0.19026",
    "e": "0.199108"
  },
  "s_19_c_9_g_o:euratl": {
    "n": "15",
    "b": "-0.199093",
    "e": "0.209287"
  },
  "s_19_c_9_g_o:europe": {
    "n": "15",
    "b": "-0.199093",
    "e": "0.209287"
  },
  "s_19_c_9_g_o:nord20": {
    "n": "23",
    "b": "-0.19026",
    "e": "0.199108"
  },
  "s_19_c_10_g_C5": {
    "n": "23",
    "b": "-0.216455",
    "e": "0.244825"
  },
  "s_19_c_10_g_o:euratl": {
    "n": "15",
    "b": "-0.258392",
    "e": "0.273625"
  },
  "s_19_c_10_g_o:europe": {
    "n": "15",
    "b": "-0.258392",
    "e": "0.273625"
  },
  "s_19_c_10_g_o:nord20": {
    "n": "23",
    "b": "-0.216455",
    "e": "0.244825"
  },
  "s_19_c_17_g_C5": {
    "n": "6",
    "b": "0.942495",
    "e": "1.54527"
  },
  "s_19_c_17_g_o:euratl": {
    "n": "4",
    "b": "1.75082",
    "e": "1.75795"
  },
  "s_19_c_17_g_o:europe": {
    "n": "4",
    "b": "1.75082",
    "e": "1.75795"
  },
  "s_19_c_17_g_o:nord20": {
    "n": "6",
    "b": "0.942495",
    "e": "1.54527"
  },
  "s_19_c_19_g_C5": {
    "n": "6",
    "b": "-0.470876",
    "e": "0.780393"
  },
  "s_19_c_19_g_o:euratl": {
    "n": "4",
    "b": "-0.166054",
    "e": "0.182816"
  },
  "s_19_c_19_g_o:europe": {
    "n": "4",
    "b": "-0.166054",
    "e": "0.182816"
  },
  "s_19_c_19_g_o:nord20": {
    "n": "6",
    "b": "-0.470876",
    "e": "0.780393"
  },
  "s_19_c_20_g_C5": {
    "n": "6",
    "b": "-0.362905",
    "e": "0.718903"
  },
  "s_19_c_20_g_o:euratl": {
    "n": "4",
    "b": "-0.121822",
    "e": "0.128039"
  },
  "s_19_c_20_g_o:europe": {
    "n": "4",
    "b": "-0.121822",
    "e": "0.128039"
  },
  "s_19_c_20_g_o:nord20": {
    "n": "6",
    "b": "-0.362905",
    "e": "0.718903"
  },
  "s_19_c_21_g_C5": {
    "n": "6",
    "b": "-0.327634",
    "e": "0.917063"
  },
  "s_19_c_21_g_o:euratl": {
    "n": "4",
    "b": "-0.161976",
    "e": "0.286494"
  },
  "s_19_c_21_g_o:europe": {
    "n": "4",
    "b": "-0.161976",
    "e": "0.286494"
  },
  "s_19_c_21_g_o:nord20": {
    "n": "6",
    "b": "-0.327634",
    "e": "0.917063"
  },
  "s_19_c_22_g_C5": {
    "n": "6",
    "b": "-0.379011",
    "e": "1.19685"
  },
  "s_19_c_22_g_o:euratl": {
    "n": "4",
    "b": "-0.291473",
    "e": "0.485044"
  },
  "s_19_c_22_g_o:europe": {
    "n": "4",
    "b": "-0.291473",
    "e": "0.485044"
  },
  "s_19_c_22_g_o:nord20": {
    "n": "6",
    "b": "-0.379011",
    "e": "1.19685"
  }
}
